postprocessor/.python-version
postprocessor/__init__.py
postprocessor/compiler.py
postprocessor/core/__init__.py
postprocessor/core/abc.py
postprocessor/core/export_pdf.py
postprocessor/core/functions/__init__.py
postprocessor/core/functions/tracks.py
postprocessor/core/group.py
postprocessor/core/lineageprocess.py
postprocessor/core/multisignal/__init__.py
postprocessor/core/multisignal/aggregate.py
postprocessor/core/multisignal/align.py
postprocessor/core/multisignal/crosscorr.py
postprocessor/core/multisignal/mi.py
postprocessor/core/processes/__init__.py
postprocessor/core/processes/autoreg.py
postprocessor/core/processes/bud_metric.py
postprocessor/core/processes/buddings.py
postprocessor/core/processes/butter.py
postprocessor/core/processes/catch22.py
postprocessor/core/processes/detrend.py
postprocessor/core/processes/dsignal.py
postprocessor/core/processes/fft.py
postprocessor/core/processes/findpeaks.py
postprocessor/core/processes/gpsignal.py
postprocessor/core/processes/knngraph.py
postprocessor/core/processes/leiden.py
postprocessor/core/processes/lineageprocess.py
postprocessor/core/processes/mednorm.py
postprocessor/core/processes/merger.py
postprocessor/core/processes/picker.py
postprocessor/core/processes/savgol.py
postprocessor/core/processes/standardscaler.py
postprocessor/core/processes/template.py
postprocessor/core/processes/umapembedding.py
postprocessor/core/processor.py
postprocessor/core/report.py
postprocessor/errors_unsegmented.txt
postprocessor/grouper.py
postprocessor/report.pdf
postprocessor/routines/__init__.py
postprocessor/routines/boxplot.py
postprocessor/routines/heatmap.py
postprocessor/routines/histogram.py
postprocessor/routines/mean_plot.py
postprocessor/routines/median_plot.py
postprocessor/routines/plot_utils.py
postprocessor/routines/plottingabc.py
postprocessor/routines/single_birth_plot.py
postprocessor/routines/single_plot.py
postprocessor/tmp.pdf
aliby_post-0.1.36.dist-info/WHEEL
aliby_post-0.1.36.dist-info/METADATA
aliby_post-0.1.36.dist-info/RECORD
